linked/__init__.py
linked/util.py
linked/datasrc/__init__.py
linked/datasrc/minidot.py
linked-0.0.4.dist-info/LICENSE
linked-0.0.4.dist-info/METADATA
linked-0.0.4.dist-info/WHEEL
linked-0.0.4.dist-info/top_level.txt
linked-0.0.4.dist-info/RECORD
