Metadata-Version: 2.1
Name: linked
Version: 0.0.4
Summary: Create and transform graphs
Home-page: https://github.com/i2mint/linked
License: apache-2.0
Platform: any
License-File: LICENSE
